asyncio_gpsd_client/__init__.py
asyncio_gpsd_client/client.py
asyncio_gpsd_client/exceptions.py
asyncio_gpsd_client/schemas.py
asyncio_gpsd_client-0.2.2.dist-info/LICENSE
asyncio_gpsd_client-0.2.2.dist-info/METADATA
asyncio_gpsd_client-0.2.2.dist-info/WHEEL
asyncio_gpsd_client-0.2.2.dist-info/RECORD
